gondi/__init__.py
gondi/api/__init__.py
gondi/api/client.py
gondi/api/inputs.py
gondi/api/query_provider.py
gondi/common_utils/__init__.py
gondi/common_utils/rpc.py
gondi/common_utils/singleton.py
gondi/common_utils/utils.py
gondi/contracts/__init__.py
gondi/contracts/abi/__init__.py
gondi/contracts/abi/address_manager.py
gondi/contracts/abi/auction_loan_liquidator.py
gondi/contracts/abi/erc_20.py
gondi/contracts/abi/multi_source_loan.py
gondi/contracts/abi/sample_collection.py
gondi/contracts/abi/sample_token.py
gondi/contracts/address_manager.py
gondi/contracts/auction_loan_liquidator.py
gondi/contracts/base_contract.py
gondi/contracts/multi_source_loan.py
gondi/contracts/sample_collection.py
gondi/contracts/sample_token.py
gondi/resources/base_schema.graphql
gondi/resources/config.goerli
gondi/resources/config.local
gondi/resources/config.main
gondi/resources/lending_schema.graphql
gondi/structs/__init__.py
gondi/structs/loan.py
gondi/structs/types.py
gondi/structs/utils.py
gondi-0.1.0.dist-info/LICENSE
gondi-0.1.0.dist-info/METADATA
gondi-0.1.0.dist-info/WHEEL
gondi-0.1.0.dist-info/RECORD
